neo4jupyter/__init__.py
neo4jupyter/neo4jupyter.py
neo4jupyter/assets/index.html
neo4jupyter-0.1.3.dist-info/LICENSE.md
neo4jupyter-0.1.3.dist-info/METADATA
neo4jupyter-0.1.3.dist-info/WHEEL
neo4jupyter-0.1.3.dist-info/top_level.txt
neo4jupyter-0.1.3.dist-info/RECORD
