Metadata-Version: 2.1
Name: neo4jupyter
Version: 0.1.3
Summary: A neo4j visualizer for Jupyter
Home-page: https://github.com/merqurio/neo4jupyter
Author: Gabriel de Maeztu
Author-email: gabriel.maeztu@gmail.com
License: MIT
Keywords: jupyter neo4j graphdb
Platform: UNKNOWN
Classifier: Development Status :: 4 - Beta
Classifier: Intended Audience :: Science/Research
Classifier: Topic :: Scientific/Engineering :: Visualization
Classifier: License :: OSI Approved :: MIT License
Classifier: Programming Language :: Python :: 3.3
Classifier: Programming Language :: Python :: 3.4
Classifier: Programming Language :: Python :: 3.5
Requires-Dist: IPython (>=4.0.0)
Requires-Dist: ipython-cypher (>=0.2.4)
Requires-Dist: py2neo
